scissors/__init__.py
scissors/cnvs.py
scissors/essentials/__init__.py
scissors/essentials/elm.py
scissors/essentials/vector.py
scissors/illustrator/__init__.py
scissors/illustrator/shapes.py
run_with_scissors-0.0.5.dist-info/LICENSE.txt
run_with_scissors-0.0.5.dist-info/METADATA
run_with_scissors-0.0.5.dist-info/WHEEL
run_with_scissors-0.0.5.dist-info/top_level.txt
run_with_scissors-0.0.5.dist-info/RECORD
