Metadata-Version: 2.1
Name: run-with-scissors
Version: 0.0.5
Summary: SVG builder
Home-page: UNKNOWN
Author: Takaaki Yoneda
Author-email: UNKNOWN
License: MIT
Keywords: SVG
Platform: UNKNOWN
Classifier: Development Status :: 5 - Production/Stable
Classifier: Intended Audience :: Education
Classifier: Operating System :: Microsoft :: Windows :: Windows 10
Classifier: License :: OSI Approved :: MIT License
Classifier: Programming Language :: Python :: 3
Requires-Dist: numpy
